file_item/__init__.py
file_item/file_item.py
file_item-1.0.0.dist-info/LICENSE
file_item-1.0.0.dist-info/METADATA
file_item-1.0.0.dist-info/WHEEL
file_item-1.0.0.dist-info/top_level.txt
file_item-1.0.0.dist-info/RECORD
