Metadata-Version: 2.1
Name: file-item
Version: 1.0.0
Summary: My file-item
Home-page: https://github.com/dmitriiweb/file-item
Author: Dmitrii K
Author-email: dmitriik@protonmail.com
License: MIT
Keywords: file-item
Platform: UNKNOWN
Classifier: Development Status :: 5 - Production/Stable
Classifier: Intended Audience :: Developers
Classifier: License :: OSI Approved :: MIT License
Classifier: Programming Language :: Python
Classifier: Programming Language :: Python :: 3.6
Classifier: Programming Language :: Python :: 3.7
Classifier: Programming Language :: Python :: 3.8
Provides-Extra: dev
Requires-Dist: coverage ; extra == 'dev'
Requires-Dist: pytest (>=3.10) ; extra == 'dev'
Requires-Dist: readme-renderer ; extra == 'dev'
Requires-Dist: sphinx ; extra == 'dev'
Requires-Dist: sphinx-rtd-theme (>=0.4.0) ; extra == 'dev'
Provides-Extra: dev-docs
Requires-Dist: readme-renderer ; extra == 'dev-docs'
Requires-Dist: sphinx ; extra == 'dev-docs'
Requires-Dist: sphinx-rtd-theme (>=0.4.0) ; extra == 'dev-docs'
Provides-Extra: dev-lint
Provides-Extra: dev-test
Requires-Dist: coverage ; extra == 'dev-test'
Requires-Dist: pytest (>=3.10) ; extra == 'dev-test'
Provides-Extra: timezone
Requires-Dist: pytz ; extra == 'timezone'
